[
        {
            "email": "rooseveltperez19@gmail.com",
            "nombre": "Roosevelt",
            "apellido": "Perez",
            "password": "12345"
        },
        {
            "email": "Jose@gmail.com",
            "nombre": "Jose",
            "apellido": "Hernandez",
            "password": "12345"
        },
        {
            "email": "Silvia@gmail.com",
            "nombre": "Silvia",
            "apellido": "Fernandez",
            "password": "12345"
        }
    ]
